Metadata-Version: 2.1
Name: apache_bot_blocker
Version: 0.1.3
Summary: Bot Blocker for server log
Home-page: https://github.com/yourusername/your-repo
Author: Albert Zheng
Author-email: anpei.zheng@gmail.com
Classifier: Programming Language :: Python :: 3
Classifier: License :: OSI Approved :: MIT License
Classifier: Operating System :: OS Independent
Requires-Python: >=3.6
License-File: LICENSE
